mobi/__init__.py
mobi/lz77.py
mobi/mobi.py
mobi/type.py
mobi_reader-0.2.1.dist-info/LICENSE
mobi_reader-0.2.1.dist-info/METADATA
mobi_reader-0.2.1.dist-info/WHEEL
mobi_reader-0.2.1.dist-info/top_level.txt
mobi_reader-0.2.1.dist-info/RECORD
